tests/__init__.py
tests/test_tradingview_websocket.py
tradingview_websocket/__init__.py
tradingview_websocket/tradingview_websocket.py
tradingview_websocket-0.5.dist-info/LICENSE.md
tradingview_websocket-0.5.dist-info/METADATA
tradingview_websocket-0.5.dist-info/WHEEL
tradingview_websocket-0.5.dist-info/top_level.txt
tradingview_websocket-0.5.dist-info/RECORD
