Metadata-Version: 2.1
Name: tradingview-websocket
Version: 0.5
Summary: This Python package provides a simple WebSocket client for connecting to the TradingView WebSocket API. It allows users to subscribe to real-time financial data streams and retrieve historical data.
Home-page: https://github.com/SerdarARIKAN/tradingview_websocket
Author: Serdar ARIKAN
Author-email: serdardarikan@gmail.com
License: UNKNOWN
Platform: UNKNOWN
Classifier: Programming Language :: Python :: 3
Classifier: License :: OSI Approved :: MIT License
Classifier: Operating System :: OS Independent
License-File: LICENSE.md
Requires-Dist: websocket-client
